csjopenapimcp/__init__.py
csjopenapimcp/model.py
csjopenapimcp/server.py
csjopenapimcp/sign.py
csj_openapi_mcp-0.1.15.dist-info/METADATA
csj_openapi_mcp-0.1.15.dist-info/WHEEL
csj_openapi_mcp-0.1.15.dist-info/entry_points.txt
csj_openapi_mcp-0.1.15.dist-info/top_level.txt
csj_openapi_mcp-0.1.15.dist-info/RECORD
