Metadata-Version: 2.4
Name: csj-openapi-mcp
Version: 0.1.15
Summary: Excel MCP Server for manipulating Excel files
Requires-Python: >=3.10
Requires-Dist: requests>=2.25.0
Requires-Dist: fastmcp
